<?xml version="1.0" encoding="UTF-8"?><record_update>
    <sys_choice action="DELETE" field="u_what_needed" table="x_58872_needit_needit" version="3">
        <sys_choice_set action="DELETE">
            <element>u_what_needed</element>
            <name>x_58872_needit_needit</name>
            <sys_class_name/>
            <sys_created_by/>
            <sys_created_on/>
            <sys_id/>
            <sys_mod_count/>
            <sys_name/>
            <sys_package/>
            <sys_policy/>
            <sys_scope/>
            <sys_update_name/>
            <sys_updated_by/>
            <sys_updated_on>2020-05-06 07:19:40</sys_updated_on>
        </sys_choice_set>
    </sys_choice>
    <sys_update_version action="INSERT_OR_UPDATE">
        <action>DELETE</action>
        <application/>
        <file_path/>
        <instance_id>1a93c2a1db88009052dd2f17d4961983</instance_id>
        <instance_name>dev93672</instance_name>
        <name>sys_choice_x_58872_needit_needit_u_what_needed</name>
        <payload><![CDATA[<?xml version="1.0" encoding="UTF-8"?><record_update><sys_choice action="DELETE" field="u_what_needed" table="x_58872_needit_needit" version="3"><sys_choice_set action="DELETE"><element>u_what_needed</element><name>x_58872_needit_needit</name><sys_class_name/><sys_created_by/><sys_created_on/><sys_id/><sys_mod_count/><sys_name/><sys_package/><sys_policy/><sys_scope/><sys_update_name/><sys_updated_by/><sys_updated_on>2020-05-06 07:19:40</sys_updated_on></sys_choice_set></sys_choice></record_update>]]></payload>
        <payload_hash>-429457270</payload_hash>
        <record_name>Task.u_what_needed</record_name>
        <reverted_from/>
        <source>d42788851b28d0100e4f4196bc4bcbe8</source>
        <source_table>sys_update_set</source_table>
        <state>previous</state>
        <sys_created_by>admin</sys_created_by>
        <sys_created_on>2020-05-06 07:19:40</sys_created_on>
        <sys_id>c5ce3da21be810100e4f4196bc4bcb19</sys_id>
        <sys_mod_count>0</sys_mod_count>
        <sys_recorded_at>171e8dab8370000001</sys_recorded_at>
        <sys_updated_by>admin</sys_updated_by>
        <sys_updated_on>2020-05-06 07:19:40</sys_updated_on>
        <type>Choice list</type>
        <update_guid>41ce3da272e81010925179062ff88e19</update_guid>
        <update_guid_history>41ce3da272e81010925179062ff88e19:-429457270,4dce3da2d7e8101068255c1739b42415:-2024862411,0dce3da2d7e81010ab84a011a3c26b12:-1462033836,c9ce3da29de81010abdbffa03323b90f:-1164073246,89ce3da2d2e8101002271816c3ecc30c:-590928877,49ce3da2a8e81010aa08237771f0c509:1850968269,09ce3da241e81010abd45fa47b91aa06:-1662330202,c5ce3da25de810105d60473c769cf403:1584791746,601291c23a60101008fb3f74b4d1d0fe:727517377</update_guid_history>
    </sys_update_version>
    <sys_metadata_delete action="INSERT_OR_UPDATE">
        <sys_audit_delete/>
        <sys_class_name>sys_metadata_delete</sys_class_name>
        <sys_created_by>admin</sys_created_by>
        <sys_created_on>2020-05-06 07:19:49</sys_created_on>
        <sys_db_object display_value="" name="sys_choice_set">sys_choice_set</sys_db_object>
        <sys_id>72ce7da21be810100e4f4196bc4bcb73</sys_id>
        <sys_metadata>72ce7da21be810100e4f4196bc4bcb73</sys_metadata>
        <sys_mod_count>0</sys_mod_count>
        <sys_name>u_what_needed</sys_name>
        <sys_package display_value="NeedIt" source="x_58872_needit">6ead8e780f603200cd674f8ce1050ed1</sys_package>
        <sys_parent/>
        <sys_policy/>
        <sys_scope display_value="NeedIt">6ead8e780f603200cd674f8ce1050ed1</sys_scope>
        <sys_scope_delete display_value="">94872a8897db403e8ee69a431de2fca4</sys_scope_delete>
        <sys_update_name>sys_choice_x_58872_needit_needit_u_what_needed</sys_update_name>
        <sys_update_version display_value="sys_choice_x_58872_needit_needit_u_what_needed">c5ce3da21be810100e4f4196bc4bcb19</sys_update_version>
        <sys_updated_by>admin</sys_updated_by>
        <sys_updated_on>2020-05-06 07:19:49</sys_updated_on>
    </sys_metadata_delete>
</record_update>
